hiccough/__init__.py
hiccough/conftest.py
hiccough-0.2.0.dist-info/LICENSE
hiccough-0.2.0.dist-info/METADATA
hiccough-0.2.0.dist-info/WHEEL
hiccough-0.2.0.dist-info/entry_points.txt
hiccough-0.2.0.dist-info/top_level.txt
hiccough-0.2.0.dist-info/RECORD
