Metadata-Version: 2.1
Name: hiccough
Version: 0.2.0
Summary: A lightweight package for html generation
Home-page: https://github.com/lkschubert8/hiccough
Author: Luke Schubert
Author-email: lkschubert8@gmail.com
License: UNKNOWN
Project-URL: Bug Tracker, https://github.com/lkschubert8/hiccough/issues
Platform: UNKNOWN
Classifier: Programming Language :: Python :: 3
Classifier: License :: OSI Approved :: MIT License
Classifier: Operating System :: OS Independent
Requires-Python: >=3.6
License-File: LICENSE
